.gitignore
CHANGES.rst
MANIFEST.in
README.rst
README.txt
setup.py
docs/HISTORY.txt
docs/INSTALL.txt
docs/LICENSE.GPL
docs/LICENSE.txt
xm/__init__.py
xm.tracker.egg-info/PKG-INFO
xm.tracker.egg-info/SOURCES.txt
xm.tracker.egg-info/dependency_links.txt
xm.tracker.egg-info/entry_points.txt
xm.tracker.egg-info/namespace_packages.txt
xm.tracker.egg-info/not-zip-safe
xm.tracker.egg-info/requires.txt
xm.tracker.egg-info/top_level.txt
xm/tracker/TODO.txt
xm/tracker/__init__.py
xm/tracker/config.py
xm/tracker/configure.zcml
xm/tracker/interfaces.py
xm/tracker/rebuild_i18n.sh
xm/tracker/tracker.py
xm/tracker/tracker.txt
xm/tracker/utils.py
xm/tracker/browser/__init__.py
xm/tracker/browser/configure.zcml
xm/tracker/browser/entries.zcml
xm/tracker/browser/entry.py
xm/tracker/browser/interfaces.py
xm/tracker/browser/ksstracker.py
xm/tracker/browser/tasks.zcml
xm/tracker/browser/tracker.py
xm/tracker/browser/tracker.zcml
xm/tracker/browser/viewlets.py
xm/tracker/browser/images/arrow_blue_inactive.gif
xm/tracker/browser/images/arrow_blue_inactive.gif.metadata
xm/tracker/browser/images/arrow_green_inactive.gif
xm/tracker/browser/images/arrow_green_inactive.gif.metadata
xm/tracker/browser/images/background_top.gif
xm/tracker/browser/images/background_top.gif.metadata
xm/tracker/browser/images/backgroundheader.gif
xm/tracker/browser/images/backgroundheader.gif.metadata
xm/tracker/browser/images/breadcrumbs_bg.gif
xm/tracker/browser/images/breadcrumbs_bg.gif.metadata
xm/tracker/browser/images/gradient-blue.gif
xm/tracker/browser/images/gradient-blue.gif.metadata
xm/tracker/browser/images/gradient-green.gif
xm/tracker/browser/images/gradient-green.gif.metadata
xm/tracker/browser/images/gradient-grey.gif
xm/tracker/browser/images/gradient-grey.gif.metadata
xm/tracker/browser/images/gradient-red.gif
xm/tracker/browser/images/gradient-red.gif.metadata
xm/tracker/browser/images/loading.gif
xm/tracker/browser/images/loading.gif.metadata
xm/tracker/browser/images/overlay.png
xm/tracker/browser/images/overlay.png.metadata
xm/tracker/browser/images/select_active.gif
xm/tracker/browser/images/select_active.gif.metadata
xm/tracker/browser/images/select_inactive.gif
xm/tracker/browser/images/select_inactive.gif.metadata
xm/tracker/browser/images/side-left-blue.gif
