Metadata-Version: 1.0
Name: xm.tracker
Version: 1.0.6
Summary: A time tracker based on the concepts of gtimelog
Home-page: https://plone.org/products/extreme-management-tool/
Author: Jean-Paul Ladage
Author-email: j.ladage@zestsoftware.nl
License: GPL
Keywords: xm timetracker
Platform: UNKNOWN
Classifier: Framework :: Plone
Classifier: Programming Language :: Python
Classifier: Topic :: Software Development :: Libraries :: Python Modules
